cs_trade/__init__.py
cs_trade/cs_trade.py
cs_trade-0.0.10.dist-info/LICENSE
cs_trade-0.0.10.dist-info/METADATA
cs_trade-0.0.10.dist-info/WHEEL
cs_trade-0.0.10.dist-info/top_level.txt
cs_trade-0.0.10.dist-info/RECORD
