Metadata-Version: 2.1
Name: cs-trade
Version: 0.0.10
Summary: UNKNOWN
Home-page: UNKNOWN
License: UNKNOWN
Platform: UNKNOWN
License-File: LICENSE
Requires-Dist: pandas (>=1.3.4)
Requires-Dist: plotly (>=5.5.0)
Requires-Dist: numpy (>=1.19.2)
